iadrive/__init__.py
iadrive/__main__.py
iadrive/core.py
iadrive/utils.py
iadrive-1.0.6.dist-info/licenses/LICENSE
tests/__init__.py
tests/test_iadrive.py
tests/test_utils.py
iadrive-1.0.6.dist-info/METADATA
iadrive-1.0.6.dist-info/WHEEL
iadrive-1.0.6.dist-info/entry_points.txt
iadrive-1.0.6.dist-info/top_level.txt
iadrive-1.0.6.dist-info/RECORD
