Metadata-Version: 2.4
Name: iadrive
Version: 1.0.6
Summary: Download Google Drive files/folders and upload them to the Internet Archive
Home-page: https://github.com/Andres9890/iadrive
Author: Andres99
License: MIT
Project-URL: homepage, https://github.com/Andres9890/iadrive
Project-URL: source, https://github.com/Andres9890/iadrive.git
Project-URL: issues, https://github.com/Andres9890/iadrive/issues
Keywords: archive.org,archiving,google drive,internet archive,file mirroring
Classifier: Development Status :: 5 - Production/Stable
Classifier: Environment :: Console
Classifier: Intended Audience :: End Users/Desktop
Classifier: Operating System :: OS Independent
Classifier: Programming Language :: Python :: 3 :: Only
Classifier: Programming Language :: Python :: 3.9
Classifier: Programming Language :: Python :: 3.10
Classifier: Programming Language :: Python :: 3.11
Classifier: Programming Language :: Python :: 3.12
Classifier: Topic :: Internet :: WWW/HTTP
Classifier: Topic :: Utilities
Requires-Python: >=3.9
License-File: LICENSE
Requires-Dist: internetarchive>=5.5.0
Requires-Dist: gdown>=5.2.0
Requires-Dist: docopt-ng>=0.9.0
Requires-Dist: python-dateutil>=2.9.0.post0
Dynamic: home-page
Dynamic: license-file
Dynamic: requires-python
